hypercadaster_ES/__init__.py
hypercadaster_ES/building_inference.py
hypercadaster_ES/downloaders.py
hypercadaster_ES/functions.py
hypercadaster_ES/interoperability.py
hypercadaster_ES/mergers.py
hypercadaster_ES/utils.py
hypercadaster_ES/cached_files/ine_inspire_codes.xlsx
hypercadaster_es-1.0.5.dist-info/LICENSE
hypercadaster_es-1.0.5.dist-info/METADATA
hypercadaster_es-1.0.5.dist-info/WHEEL
hypercadaster_es-1.0.5.dist-info/top_level.txt
hypercadaster_es-1.0.5.dist-info/RECORD
