Metadata-Version: 2.1
Name: hypercadaster_es
Version: 1.0.5
Summary: Python library to obtain the Spanish cadaster data joined with external attributes.
Home-page: https://github.com/BeeGroup-cimne
Author: Jose Manuel Broto Vispe
Author-email: jmbrotovispe@gmail.com
License: EUPL-1.2
Keywords: cadastral data,geospatial,spain,gis,real estate
Classifier: Development Status :: 4 - Beta
Classifier: Intended Audience :: Developers
Classifier: Intended Audience :: Science/Research
Classifier: License :: OSI Approved :: European Union Public Licence 1.2 (EUPL 1.2)
Classifier: Programming Language :: Python :: 3
Classifier: Programming Language :: Python :: 3.10
Classifier: Programming Language :: Python :: 3.11
Classifier: Programming Language :: Python :: 3.12
Classifier: Topic :: Scientific/Engineering :: GIS
Classifier: Topic :: Software Development :: Libraries :: Python Modules
Classifier: Operating System :: OS Independent
Requires-Python: >=3.10
License-File: LICENSE
Requires-Dist: numpy <3.0,>=1.24
Requires-Dist: scipy <2.0,>=1.10
Requires-Dist: pandas <3.0,>=2.1
Requires-Dist: polars <2.0,>=1.0
Requires-Dist: scikit-learn <2.0,>=1.3
Requires-Dist: joblib >=1.3
Requires-Dist: threadpoolctl >=3.3
Requires-Dist: dask >=2024.4
Requires-Dist: cloudpickle >=3.0
Requires-Dist: toolz >=0.12
Requires-Dist: partd >=1.4
Requires-Dist: shapely <3.0,>=2.0
Requires-Dist: pyproj <4.0,>=3.5
Requires-Dist: rasterio <2.0,>=1.3
Requires-Dist: fiona <2.0,>=1.9
Requires-Dist: geopandas <1.1,>=0.13
Requires-Dist: pyogrio <1.0,>=0.8
Requires-Dist: affine >=2.4
Requires-Dist: snuggs >=1.4
Requires-Dist: pygeoif >=0.7
Requires-Dist: osmnx <2.1,>=1.8
Requires-Dist: networkx >=3.2
Requires-Dist: pyarrow >=14.0
Requires-Dist: openpyxl >=3.1
Requires-Dist: et-xmlfile >=1.1
Requires-Dist: arrow >=1.4.0
Requires-Dist: fastkml >=1.4.0
Requires-Dist: lxml >=6.0.2
Requires-Dist: requests <3.0,>=2.31
Requires-Dist: urllib3 <3,>=2.1
Requires-Dist: charset-normalizer >=3.3
Requires-Dist: idna >=3.6
Requires-Dist: certifi >=2024.2
Requires-Dist: beautifulsoup4 >=4.12
Requires-Dist: soupsieve >=2.5
Requires-Dist: xmltodict >=0.13
Requires-Dist: matplotlib <4,>=3.8
Requires-Dist: contourpy >=1.2
Requires-Dist: cycler >=0.12
Requires-Dist: kiwisolver >=1.4
Requires-Dist: fonttools >=4.53
Requires-Dist: pillow >=10.2
Requires-Dist: click >=8.1
Requires-Dist: click-plugins >=1.1
Requires-Dist: cligj >=0.7
Requires-Dist: packaging >=23.2
Requires-Dist: python-dateutil >=2.8.2
Requires-Dist: pytz >=2024.1
Requires-Dist: tzdata >=2024.1
Requires-Dist: regex <2027.0,>=2023.12
Requires-Dist: tqdm >=4.66
Requires-Dist: six >=1.16
Requires-Dist: PyYAML >=6.0
Provides-Extra: dev
Requires-Dist: black >=24.0 ; extra == 'dev'
Requires-Dist: ruff >=0.4 ; extra == 'dev'
Requires-Dist: pytest >=7.0 ; extra == 'dev'
Requires-Dist: pytest-cov >=4.0 ; extra == 'dev'
